{
    "chartOne": "import React from 'react'; import Chart from 'react-apexcharts'; const QuestionResponseFlowMap = () => { const series = [{ name: 'Correct', data: [45, 20, 15, 20] }, { name: 'Ambiguous', data: [20, 10, 15, 5] }, { name: 'Unanswered', data: [10, 5, 10, 5] }]; const options = { chart: { type: 'bar', height: 350 }, xaxis: { categories: ['Q1', 'Q2', 'Q3', 'Q4'] } }; return <Chart options={options} series={series} type=\"bar\" height={350} />; }; export default QuestionResponseFlowMap;",
    "chartTwo": "import React from 'react'; import Chart from 'react-apexcharts'; const SentimentAnalysis = () => { const series = [{ name: 'Sentiment', data: [70, 20, 10] }]; const options = { chart: { type: 'bar', height: 350 }, xaxis: { categories: ['Positive', 'Negative', 'Neutral'] } }; return <Chart options={options} series={series} type=\"bar\" height={350} />; }; export default SentimentAnalysis;",
    "chartThree": "import React from 'react'; import Chart from 'react-apexcharts'; const TopicClusters = () => { const series = [{ name: 'Topics', data: [35, 30, 25, 20] }]; const options = { chart: { type: 'bubble', height: 350 }, xaxis: { categories: ['Topic A', 'Topic B', 'Topic C', 'Topic D'] } }; return <Chart options={options} series={series} type=\"bubble\" height={350} />; }; export default TopicClusters;",
    "chartFour": "import React from 'react'; import Chart from 'react-apexcharts'; const QuestionsTrendAnalysis = () => { const series = [{ name: 'Questions', data: [20, 30, 50, 40, 60] }]; const options = { chart: { type: 'line', height: 350 }, xaxis: { categories: ['Day 1', 'Day 2', 'Day 3', 'Day 4', 'Day 5'] } }; return <Chart options={options} series={series} type=\"line\" height={350} />; }; export default QuestionsTrendAnalysis;",
    "chartFive": "import React from 'react'; import Chart from 'react-apexcharts'; const ComplexityResponseTime = () => { const series = [{ name: 'Complexity', data: [5, 10, 15, 20] }]; const options = { chart: { type: 'scatter', height: 350 }, xaxis: { categories: ['Low', 'Medium', 'High'] } }; return <Chart options={options} series={series} type=\"scatter\" height={350} />; }; export default ComplexityResponseTime;"
}
